Workbook

Sheet BD
A1: Nombre del empleado | B1: ID | C1: Puntuación rendimiento ID | D1: Salario mensual corregido | E1: Cargo | F1: Fecha de Nacimiento | G1: Sexo | H1: Estado Civil | I1: Fecha de Contratación | J1: Fecha de Salida | K1: Motivo Salida | L1: Estado de miembro | M1: Departamento | N1: Fuente Reclutamiento | O1: Registro de rendimiento | P1: Encuesta de compromiso | Q1: Índice de Satisfacción | R1: SpecialProjectsCount | S1: Última atualización de rendimiento | T1: Tiempo Medio Años
A2: Agustina Morales | B2: 1304055947 | C2: 4 | D2: 5060 | E2: Técnico de Producción I | F2: 30092 | G2: F | H2: Soltero | I2: 43709 | K2: N/A - Empleado | L2: Activo | M2: Producción | N2: Web de la Empresa | O2: Por encima de lo Esperado | P2: 5 | Q2: 5 | R2: 0 | S2: 44166 | T2: =IF(L2="Activo",(DATE(2024,1,1)-I2)/365,(J2-I2)/365) -> 4.3369863
A3: Lucas Figueroa | B3: 1109029366 | C3: 3 | D3: 3520 | E3: Técnico de Producción I | F3: 27749 | G3: M | H3: Soltero | I3: 43499 | K3: N/A - Empleado | L3: Activo | M3: Producción | N3: Indicación de empleados | O3: Dentro de lo Esperado | P3: 5 | Q3: 3 | R3: 0 | S3: 44166 | T3: =IF(L3="Activo",(DATE(2024,1,1)-I3)/365,(J3-I3)/365) -> 4.9123288
A4: Marcos Rodríguez | B4: 1501072124 | C4: 1 | D4: 4400 | E4: Técnico de Producción I | F4: 26406 | G4: M | H4: Casado(a) | I4: 44383 | K4: N/A - Empleado | L4: Activo | M4: Producción | N4: Web de empleo | O4: Por debajo de lo esperado | P4: 1.12 | Q4: 2 | R4: 0 | S4: 44166 | T4: =IF(L4="Activo",(DATE(2024,1,1)-I4)/365,(J4-I4)/365) -> 2.490411
A5: Juan Pérez | B5: 1302053339 | C5: 1 | D5: 3960 | E5: Técnico de Producción I | F5: 34624 | G5: M | H5: Casado(a) | I5: 44869 | K5: N/A - Empleado | L5: Activo | M5: Producción | N5: Web de empleo | O5: Por debajo de lo esperado | P5: 1.56 | Q5: 4 | R5: 0 | S5: 44166 | T5: =IF(L5="Activo",(DATE(2024,1,1)-I5)/365,(J5-I5)/365) -> 1.1589041
A6: Lucía Fernández | B6: 1204032927 | C6: 4 | D6: 3520 | E6: Técnico de Producción I | F6: 31263 | G6: F | H6: Soltero | I6: 44467 | K6: N/A - Empleado | L6: Activo | M6: Producción | N6: Feria de empleo | O6: Por encima de lo Esperado | P6: 3.39 | Q6: 4 | R6: 0 | S6: 44166 | T6: =IF(L6="Activo",(DATE(2024,1,1)-I6)/365,(J6-I6)/365) -> 2.260274
A7: Emma López | B7: 1404066622 | C7: 4 | D7: 4400 | E7: Técnico de Producción I | F7: 28890 | G7: F | H7: Casado(a) | I7: 44534 | K7: N/A - Empleado | L7: Activo | M7: Producción | N7: Web de empleo | O7: Por encima de lo Esperado | P7: 4.76 | Q7: 4 | R7: 0 | S7: 44166 | T7: =IF(L7="Activo",(DATE(2024,1,1)-I7)/365,(J7-I7)/365) -> 2.0767123
A8: Sofía Ramírez | B8: 1205033102 | C8: 3 | D8: 3300 | E8: Técnico de Producción I | F8: 33108 | G8: F | H8: Casado(a) | I8: 44061 | K8: N/A - Empleado | L8: Activo | M8: Producción | N8: Web de empleo | O8: Dentro de lo Esperado | P8: 4.81 | Q8: 4 | R8: 0 | S8: 44166 | T8: =IF(L8="Activo",(DATE(2024,1,1)-I8)/365,(J8-I8)/365) -> 3.3726027
A9: Lisa Sánchez | B9: 1308060366 | C9: 4 | D9: 3520 | E9: Técnico de Producción I | F9: 34342 | G9: F | H9: Casado(a) | I9: 44383 | K9: N/A - Empleado | L9: Activo | M9: Producción | N9: Feria de empleo | O9: Por encima de lo Esperado | P9: 5 | Q9: 3.1 | R9: 0 | S9: 44166 | T9: =IF(L9="Activo",(DATE(2024,1,1)-I9)/365,(J9-I9)/365) -> 2.490411
A10: Valerio Romero | B10: 1407069280 | C10: 4 | D10: 5445 | E10: Técnico de Producción I | F10: 31284 | G10: M | H10: Casado(a) | I10: 45084 | K10: N/A - Empleado | L10: Activo | M10: Producción | N10: Indicación de empleados | O10: Por encima de lo Esperado | P10: 1.97 | Q10: 4 | R10: 0 | S10: 44166 | T10: =IF(L10="Activo",(DATE(2024,1,1)-I10)/365,(J10-I10)/365) -> 0.56986301
A11: Hanna Torres | B11: 1209048696 | C11: 2 | D11: 4840 | E11: Técnico de Producción I | F11: 30358 | G11: F | H11: Casado(a) | I11: 44012 | K11: N/A - Empleado | L11: Activo | M11: Producción | N11: Web de empleo | O11: Por debajo de lo esperado | P11: 3.88 | Q11: 3 | R11: 0 | S11: 44166 | T11: =IF(L11="Activo",(DATE(2024,1,1)-I11)/365,(J11-I11)/365) -> 3.5068493
A12: Camila Álvarez | B12: 1006020020 | C12: 3 | D12: 5280 | E12: Técnico de Producción I | F12: 31486 | G12: F | H12: Casado(a) | I12: 43709 | K12: N/A - Empleado | L12: Activo | M12: Producción | N12: Web de la Empresa | O12: Dentro de lo Esperado | P12: 5 | Q12: 5 | R12: 0 | S12: 44166 | T12: =IF(L12="Activo",(DATE(2024,1,1)-I12)/365,(J12-I12)/365) -> 4.3369863
A13: Cristina Ruiz | B13: 1408069882 | C13: 3 | D13: 3520 | E13: Técnico de Producción I | F13: 35091 | G13: F | H13: Soltero | I13: 44061 | K13: N/A - Empleado | L13: Activo | M13: Producción | N13: Feria de empleo | O13: Dentro de lo Esperado | P13: 3.99 | Q13: 3 | R13: 0 | S13: 44166 | T13: =IF(L13="Activo",(DATE(2024,1,1)-I13)/365,(J13-I13)/365) -> 3.3726027
... A22: Julio Acosta | B22: 1106026579 | C22: 3 | D22: 3300 | E22: Técnico de Producción I | F22: 30821 | G22: M | H22: Casado(a) | I22: 43502 | K22: N/A - Empleado | L22: Activo | M22: Producción | N22: Web de la Empresa | O22: Dentro de lo Esperado | P22: 5 | Q22: 3 | R22: 0 | S22: 44166 | T22: =IF(L22="Activo",(DATE(2024,1,1)-I22)/365,(J22-I22)/365) -> 4.9041096
A23: Maite Benítez | B23: 1201431438 | C23: 3 | D23: 4400 | E23: Técnico de Producción I | F23: 28437 | G23: F | H23: Soltero | I23: 43596 | K23: N/A - Empleado | L23: Activo | M23: Producción | N23: Web de empleo | O23: Dentro de lo Esperado | P23: 2.32 | Q23: 3 | R23: 0 | S23: 44166 | T23: =IF(L23="Activo",(DATE(2024,1,1)-I23)/365,(J23-I23)/365) -> 4.6465753
A24: Lucas Cabrera | B24: 1304055987 | C24: 3 | D24: 3740 | E24: Técnico de Producción I | F24: 33492 | G24: M | H24: Casado(a) | I24: 43715 | K24: N/A - Empleado | L24: Activo | M24: Producción | N24: Web de empleo | O24: Dentro de lo Esperado | P24: 5 | Q24: 5 | R24: 0 | S24: 44166 | T24: =IF(L24="Activo",(DATE(2024,1,1)-I24)/365,(J24-I24)/365) -> 4.3205479
A25: Inxgel Domínguez | B25: 1401064327 | C25: 3 | D25: 4400 | E25: Técnico de Producción I | F25: 30276 | G25: F | H25: Casado(a) | I25: 43250 | K25: N/A - Empleado | L25: Activo | M25: Producción | N25: Feria de empleo | O25: Dentro de lo Esperado | P25: 5 | Q25: 4 | R25: 0 | S25: 44166 | T25: =IF(L25="Activo",(DATE(2024,1,1)-I25)/365,(J25-I25)/365) -> 5.5945205
A26: Natalia Peralta | B26: 1203032357 | C26: 3 | D26: 4180 | E26: Técnico de Producción I | F26: 32695 | G26: F | H26: Soltero | I26: 44049 | K26: N/A - Empleado | L26: Activo | M26: Producción | N26: Indicación de empleados | O26: Dentro de lo Esperado | P26: 2.79 | Q26: 5 | R26: 0 | S26: 44166 | T26: =IF(L26="Activo",(DATE(2024,1,1)-I26)/365,(J26-I26)/365) -> 3.4054795
A27: Gonzalo Suárez | B27: 1001735072 | C27: 3 | D27: 3740 | E27: Técnico de Producción I | F27: 31738 | G27: M | H27: Soltero | I27: 41769 | K27: N/A - Empleado | L27: Activo | M27: Producción | N27: Web de empleo | O27: Dentro de lo Esperado | P27: 3.66 | Q27: 3 | R27: 0 | S27: 44166 | T27: =IF(L27="Activo",(DATE(2024,1,1)-I27)/365,(J27-I27)/365) -> 9.6520548
A28: Rocío Figueroa | B28: 710007555 | C28: 3 | D28: 3740 | E28: Técnico de Producción I | F28: 28986 | G28: F | H28: Soltero | I28: 44347 | K28: N/A - Empleado | L28: Activo | M28: Producción | N28: Web de empleo | O28: Dentro de lo Esperado | P28: 5 | Q28: 4 | R28: 0 | S28: 44166 | T28: =IF(L28="Activo",(DATE(2024,1,1)-I28)/365,(J28-I28)/365) -> 2.5890411
A29: Tamara Correa | B29: 1012023152 | C29: 2 | D29: 4840 | E29: Técnico de Producción I | F29: 32277 | G29: F | H29: Soltero | I29: 44243 | K29: N/A - Empleado | L29: Activo | M29: Producción | N29: Web de empleo | O29: Por debajo de lo esperado | P29: 2.44 | Q29: 3 | R29: 0 | S29: 44166 | T29: =IF(L29="Activo",(DATE(2024,1,1)-I29)/365,(J29-I29)/365) -> 2.8739726
A30: Melina Arias | B30: 1211051232 | C30: 3 | D30: 3300 | E30: Técnico de Producción I | F30: 30544 | G30: F | H30: Soltero | I30: 44467 | K30: N/A - Empleado | L30: Activo | M30: Producción | N30: Feria de empleo | O30: Dentro de lo Esperado | P30: 1.24 | Q30: 5 | R30: 0 | S30: 44166 | T30: =IF(L30="Activo",(DATE(2024,1,1)-I30)/365,(J30-I30)/365) -> 2.260274
A31: Francis Ponce | B31: 1011022883 | C31: 3 | D31: 4620 | E31: Técnico de Producción I | F31: 34238 | G31: F | H31: Casado(a) | I31: 42186 | K31: N/A - Empleado | L31: Activo | M31: Producción | N31: Web de la Empresa | O31: Dentro de lo Esperado | P31: 4.84 | Q31: 5 | R31: 0 | S31: 44166 | T31: =IF(L31="Activo",(DATE(2024,1,1)-I31)/365,(J31-I31)/365) -> 8.509589
A32: Daniela Moya | B32: 1403066194 | C32: 3 | D32: 4840 | E32: Técnico de Producción I | F32: 27693 | G32: F | H32: Soltero | I32: 43193 | K32: N/A - Empleado | L32: Activo | M32: Producción | N32: Web de empleo | O32: Dentro de lo Esperado | P32: 5 | Q32: 5 | R32: 0 | S32: 44166 | T32: =IF(L32="Activo",(DATE(2024,1,1)-I32)/365,(J32-I32)/365) -> 5.7506849
A33: Alejandra Ibáñez | B33: 1305057282 | C33: 3 | D33: 4290 | E33: Técnico de Producción I | F33: 31016 | G33: F | H33: Soltero | I33: 44534 | K33: N/A - Empleado | L33: Activo | M33: Producción | N33: Web de empleo | O33: Dentro de lo Esperado | P33: 2.73 | Q33: 4 | R33: 0 | S33: 44166 | T33: =IF(L33="Activo",(DATE(2024,1,1)-I33)/365,(J33-I33)/365) -> 2.0767123
A34: Micaela Soto | B34: 1001109612 | C34: 3 | D34: 3300 | E34: Técnico de Producción I | F34: 30446 | G34: F | H34: Casado(a) | I34: 43502 | K34: N/A - Empleado | L34: Activo | M34: Producción | N34: Web de la Empresa | O34: Dentro de lo Esperado | P34: 5 | Q34: 3 | R34: 0 | S34: 44166 | T34: =IF(L34="Activo",(DATE(2024,1,1)-I34)/365,(J34-I34)/365) -> 4.9041096
A35: Emanuel Luna | B35: 1406068241 | C35: 3 | D35: 4620 | E35: Técnico de Producción I | F35: 31816 | G35: M | H35: Casado(a) | I35: 43599 | K35: N/A - Empleado | L35: Activo | M35: Producción | N35: Web de empleo | O35: Dentro de lo Esperado | P35: 1.83 | Q35: 3 | R35: 0 | S35: 44166 | T35: =IF(L35="Activo",(DATE(2024,1,1)-I35)/365,(J35-I35)/365) -> 4.6383562
... A54: Paola Maidana | B54: 1408069539 | C54: 3 | D54: 3740 | E54: Técnico de Producción I | F54: 35598 | G54: F | H54: Soltero | I54: 44145 | K54: N/A - Empleado | L54: Activo | M54: Producción | N54: Web de empleo | O54: Dentro de lo Esperado | P54: 1.94 | Q54: 5 | R54: 0 | S54: 44166 | T54: =IF(L54="Activo",(DATE(2024,1,1)-I54)/365,(J54-I54)/365) -> 3.1424658
A55: Kevin Barrios | B55: 1002021900 | C55: 3 | D55: 4180 | E55: Técnico de Producción I | F55: 32598 | G55: M | H55: Soltero | I55: 43690 | K55: N/A - Empleado | L55: Activo | M55: Producción | N55: Web de la Empresa | O55: Dentro de lo Esperado | P55: 4.17 | Q55: 4 | R55: 0 | S55: 44166 | T55: =IF(L55="Activo",(DATE(2024,1,1)-I55)/365,(J55-I55)/365) -> 4.3890411
A56: Roque Páez | B56: 1304055683 | C56: 3 | D56: 3080 | E56: Técnico de Producción I | F56: 30234 | G56: M | H56: Soltero | I56: 44243 | K56: N/A - Empleado | L56: Activo | M56: Producción | N56: Feria de empleo | O56: Dentro de lo Esperado | P56: 2.79 | Q56: 3 | R56: 0 | S56: 44166 | T56: =IF(L56="Activo",(DATE(2024,1,1)-I56)/365,(J56-I56)/365) -> 2.8739726
A57: Ana Duarte | B57: 1209049259 | C57: 3 | D57: 3740 | E57: Técnico de Producción I | F57: 33425 | G57: F | H57: Soltero | I57: 44347 | K57: N/A - Empleado | L57: Activo | M57: Producción | N57: Web de empleo | O57: Dentro de lo Esperado | P57: 2.55 | Q57: 4 | R57: 0 | S57: 44166 | T57: =IF(L57="Activo",(DATE(2024,1,1)-I57)/365,(J57-I57)/365) -> 2.5890411
A58: Andrea Gallardo | B58: 1307059944 | C58: 3 | D58: 3740 | E58: Técnico de Producción I | F58: 28755 | G58: F | H58: Casado(a) | I58: 42850 | K58: N/A - Empleado | L58: Activo | M58: Producción | N58: Web de empleo | O58: Dentro de lo Esperado | P58: 2.72 | Q58: 3 | R58: 0 | S58: 44166 | T58: =IF(L58="Activo",(DATE(2024,1,1)-I58)/365,(J58-I58)/365) -> 6.690411
A59: Malena Roldán | B59: 1501071909 | C59: 3 | D59: 5390 | E59: Técnico de Producción I | F59: 25600 | G59: F | H59: Soltero | I59: 44145 | K59: N/A - Empleado | L59: Activo | M59: Producción | N59: Indicación de empleados | O59: Dentro de lo Esperado | P59: 3.73 | Q59: 3 | R59: 0 | S59: 44166 | T59: =IF(L59="Activo",(DATE(2024,1,1)-I59)/365,(J59-I59)/365) -> 3.1424658
A60: Yamil Reynoso | B60: 1104025414 | C60: 3 | D60: 3960 | E60: Técnico de Producción I | F60: 31154 | G60: M | H60: Soltero | I60: 44049 | K60: N/A - Empleado | L60: Activo | M60: Producción | N60: Feria de empleo | O60: Dentro de lo Esperado | P60: 2.61 | Q60: 4 | R60: 0 | S60: 44166 | T60: =IF(L60="Activo",(DATE(2024,1,1)-I60)/365,(J60-I60)/365) -> 3.4054795
A61: Estela Cáceres | B61: 1503072857 | C61: 3 | D61: 4620 | E61: Técnico de Producción I | F61: 26013 | G61: F | H61: Soltero | I61: 44103 | K61: N/A - Empleado | L61: Activo | M61: Producción | N61: Indicación de empleados | O61: Dentro de lo Esperado | P61: 2.05 | Q61: 5 | R61: 0 | S61: 44166 | T61: =IF(L61="Activo",(DATE(2024,1,1)-I61)/365,(J61-I61)/365) -> 3.2575342
A62: Karen Escobar | B62: 909015167 | C62: 3 | D62: 5280 | E62: Técnico de Producción I | F62: 33784 | G62: F | H62: Casado(a) | I62: 44012 | K62: N/A - Empleado | L62: Activo | M62: Producción | N62: Web de empleo | O62: Dentro de lo Esperado | P62: 3.93 | Q62: 3 | R62: 0 | S62: 44166 | T62: =IF(L62="Activo",(DATE(2024,1,1)-I62)/365,(J62-I62)/365) -> 3.5068493
A63: Lucía Bravo | B63: 1111030244 | C63: 3 | D63: 3080 | E63: Técnico de Producción I | F63: 32013 | G63: F | H63: Soltero | I63: 43373 | K63: N/A - Empleado | L63: Activo | M63: Producción | N63: Indicación de empleados | O63: Dentro de lo Esperado | P63: 1.05 | Q63: 4 | R63: 0 | S63: 44166 | T63: =IF(L63="Activo",(DATE(2024,1,1)-I63)/365,(J63-I63)/365) -> 5.2575342
A64: Gregorio Salas | B64: 1409070522 | C64: 4 | D64: 4400 | E64: Técnico de Producción I | F64: 32421 | G64: M | H64: Soltero | I64: 43226 | K64: N/A - Empleado | L64: Activo | M64: Producción | N64: Web de la Empresa | O64: Por encima de lo Esperado | P64: 2.51 | Q64: 5 | R64: 0 | S64: 44166 | T64: =IF(L64="Activo",(DATE(2024,1,1)-I64)/365,(J64-I64)/365) -> 5.660274
A65: Ivanna Montoya | B65: 1208048062 | C65: 3 | D65: 3520 | E65: Técnico de Producción I | F65: 20485 | G65: F | H65: Soltero | I65: 44467 | K65: N/A - Empleado | L65: Activo | M65: Producción | N65: Web de empleo | O65: Dentro de lo Esperado | P65: 5 | Q65: 4 | R65: 0 | S65: 44166 | T65: =IF(L65="Activo",(DATE(2024,1,1)-I65)/365,(J65-I65)/365) -> 2.260274
A66: Marisol Antúnez | B66: 1311063172 | C66: 3 | D66: 4345 | E66: Técnico de Producción I | F66: 33879 | G66: F | H66: Soltero | I66: 45084 | K66: N/A - Empleado | L66: Activo | M66: Producción | N66: Web de empleo | O66: Dentro de lo Esperado | P66: 4.12 | Q66: 5 | R66: 0 | S66: 44166 | T66: =IF(L66="Activo",(DATE(2024,1,1)-I66)/365,(J66-I66)/365) -> 0.56986301
A67: Josefina Valdez | B67: 1501072192 | C67: 3 | D67: 4180 | E67: Técnico de Producción I | F67: 34708 | G67: F | H67: Casado(a) | I67: 44649 | K67: N/A - Empleado | L67: Activo | M67: Producción | N67: Feria de empleo | O67: Dentro de lo Esperado | P67: 3.73 | Q67: 3 | R67: 0 | S67: 44166 | T67: =IF(L67="Activo",(DATE(2024,1,1)-I67)/365,(J67-I67)/365) -> 1.7616438
... A71: Rodrigo Méndez | B71: 1103024335 | C71: 2 | D71: 4840 | E71: Técnico de Producción I | F71: 31008 | G71: M | H71: Soltero | I71: 44243 | K71: N/A - Empleado | L71: Activo | M71: Producción | N71: Web de la Empresa | O71: Por debajo de lo esperado | P71: 4.25 | Q71: 3 | R71: 0 | S71: 44166 | T71: =IF(L71="Activo",(DATE(2024,1,1)-I71)/365,(J71-I71)/365) -> 2.8739726
A72: Alejandro Palacios | B72: 1201431310 | C72: 3 | D72: 4180 | E72: Técnico de Producción I | F72: 31967 | G72: M | H72: Casado(a) | I72: 44681 | K72: N/A - Empleado | L72: Activo | M72: Producción | N72: Indicación de empleados | O72: Dentro de lo Esperado | P72: 4.36 | Q72: 5 | R72: 0 | S72: 44166 | T72: =IF(L72="Activo",(DATE(2024,1,1)-I72)/365,(J72-I72)/365) -> 1.6739726
A73: Cristal Miranda | B73: 1106026474 | C73: 3 | D73: 4400 | E73: Técnico de Producción I | F73: 33027 | G73: F | H73: Soltero | I73: 44687 | K73: N/A - Empleado | L73: Activo | M73: Producción | N73: Web de empleo | O73: Dentro de lo Esperado | P73: 3.21 | Q73: 3 | R73: 0 | S73: 44166 | T73: =IF(L73="Activo",(DATE(2024,1,1)-I73)/365,(J73-I73)/365) -> 1.6575342
A74: Mateo Leiva | B74: 1111030129 | C74: 3 | D74: 4840 | E74: Técnico de Producción I | F74: 32377 | G74: M | H74: Soltero | I74: 44049 | K74: N/A - Empleado | L74: Activo | M74: Producción | N74: Web de empleo | O74: Dentro de lo Esperado | P74: 3.8 | Q74: 5 | R74: 0 | S74: 44166 | T74: =IF(L74="Activo",(DATE(2024,1,1)-I74)/365,(J74-I74)/365) -> 3.4054795
A75: Brittany Flores | B75: 1405067642 | C75: 4 | D75: 4840 | E75: Técnico de Producción I | F75: 28824 | G75: F | H75: Casado(a) | I75: 43431 | K75: N/A - Empleado | L75: Activo | M75: Producción | N75: Web de empleo | O75: Por encima de lo Esperado | P75: 4.36 | Q75: 5 | R75: 0 | S75: 44166 | T75: =IF(L75="Activo",(DATE(2024,1,1)-I75)/365,(J75-I75)/365) -> 5.0986301
A76: Daniel Coronel | B76: 1411071212 | C76: 4 | D76: 3520 | E76: Técnico de Producción I | F76: 27300 | G76: M | H76: Soltero | I76: 43410 | K76: N/A - Empleado | L76: Activo | M76: Producción | N76: Feria de empleo | O76: Por encima de lo Esperado | P76: 1.83 | Q76: 4 | R76: 0 | S76: 44166 | T76: =IF(L76="Activo",(DATE(2024,1,1)-I76)/365,(J76-I76)/365) -> 5.1561644
A77: Lorena Giménez | B77: 1403066020 | C77: 4 | D77: 3300 | E77: Técnico de Producción I | F77: 26362 | G77: F | H77: Soltero | I77: 43834 | K77: N/A - Empleado | L77: Activo | M77: Producción | N77: Feria de empleo | O77: Por encima de lo Esperado | P77: 1.12 | Q77: 3.5 | R77: 0 | S77: 44166 | T77: =IF(L77="Activo",(DATE(2024,1,1)-I77)/365,(J77-I77)/365) -> 3.9945205
A78: Constanza Lucero | B78: 1410070998 | C78: 2 | D78: 4400 | E78: Técnico de Producción I | F78: 26820 | G78: F | H78: Soltero | I78: 45023 | K78: N/A - Empleado | L78: Activo | M78: Producción | N78: Web de la Empresa | O78: Por debajo de lo esperado | P78: 1.12 | Q78: 4 | R78: 0 | S78: 44166 | T78: =IF(L78="Activo",(DATE(2024,1,1)-I78)/365,(J78-I78)/365) -> 0.7369863
A79: Maia Arce | B79: 1212051409 | C79: 3 | D79: 4840 | E79: Técnico de Producción I | F79: 27699 | G79: F | H79: Soltero | I79: 42527 | K79: N/A - Empleado | L79: Activo | M79: Producción | N79: Feria de empleo | O79: Dentro de lo Esperado | P79: 4.46 | Q79: 3 | R79: 0 | S79: 44166 | T79: =IF(L79="Activo",(DATE(2024,1,1)-I79)/365,(J79-I79)/365) -> 7.5753425
A80: Claudia Nieto | B80: 1101023353 | C80: 3 | D80: 4400 | E80: Técnico de Producción I | F80: 29514 | G80: F | H80: Casado(a) | I80: 44607 | K80: N/A - Empleado | L80: Activo | M80: Producción | N80: Web de empleo | O80: Dentro de lo Esperado | P80: 5 | Q80: 3 | R80: 0 | S80: 44166 | T80: =IF(L80="Activo",(DATE(2024,1,1)-I80)/365,(J80-I80)/365) -> 1.8767123
A81: Ezequiel Basualdo | B81: 1302053044 | C81: 3 | D81: 4620 | E81: Técnico de Producción I | F81: 30166 | G81: M | H81: Casado(a) | I81: 44534 | K81: N/A - Empleado | L81: Activo | M81: Producción | N81: Feria de empleo | O81: Dentro de lo Esperado | P81: 5 | Q81: 5 | R81: 0 | S81: 44166 | T81: =IF(L81="Activo",(DATE(2024,1,1)-I81)/365,(J81-I81)/365) -> 2.0767123
A82: Florencia Prieto | B82: 1408069635 | C82: 3 | D82: 4400 | E82: Técnico de Producción I | F82: 27331 | G82: F | H82: Soltero | I82: 44145 | K82: N/A - Empleado | L82: Activo | M82: Producción | N82: Feria de empleo | O82: Dentro de lo Esperado | P82: 2.83 | Q82: 5 | R82: 0 | S82: 44166 | T82: =IF(L82="Activo",(DATE(2024,1,1)-I82)/365,(J82-I82)/365) -> 3.1424658
A83: Mariana Aguirre | B83: 1312063675 | C83: 3 | D83: 5280 | E83: Técnico de Producción I | F83: 29107 | G83: F | H83: Casado(a) | I83: 44061 | K83: N/A - Empleado | L83: Activo | M83: Producción | N83: Feria de empleo | O83: Dentro de lo Esperado | P83: 1.71 | Q83: 5 | R83: 0 | S83: 44166 | T83: =IF(L83="Activo",(DATE(2024,1,1)-I83)/365,(J83-I83)/365) -> 3.3726027
A84: Jesús Robles | B84: 1110029777 | C84: 3 | D84: 3740 | E84: Técnico de Producción I | F84: 30835 | G84: M | H84: Soltero | I84: 44049 | K84: N/A - Empleado | L84: Activo | M84: Producción | N84: Web de la Empresa | O84: Dentro de lo Esperado | P84: 1.09 | Q84: 4 | R84: 0 | S84: 44166 | T84: =IF(L84="Activo",(DATE(2024,1,1)-I84)/365,(J84-I84)/365) -> 3.4054795
... A92: Kevin Mansilla | B92: 1306057978 | C92: 1 | D92: 5500 | E92: Analista Comercial I | F92: 29261 | G92: M | H92: Soltero | I92: 44467 | K92: N/A - Empleado | L92: Activo | M92: Ventas | N92: Web de la Empresa | O92: Por debajo de lo esperado | P92: 1.93 | Q92: 3 | R92: 0 | S92: 44166 | T92: =IF(L92="Activo",(DATE(2024,1,1)-I92)/365,(J92-I92)/365) -> 2.260274
A93: Carlos Paredes | B93: 812015761 | C93: 3 | D93: 5400 | E93: Analista Comercial I | F93: 31915 | G93: M | H93: Soltero | I93: 44681 | K93: N/A - Empleado | L93: Activo | M93: Ventas | N93: Web de empleo | O93: Dentro de lo Esperado | P93: 5 | Q93: 5 | R93: 0 | S93: 44166 | T93: =IF(L93="Activo",(DATE(2024,1,1)-I93)/365,(J93-I93)/365) -> 1.6739726
A94: Romal Funes | B94: 1411071295 | C94: 3 | D94: 5350 | E94: Analista Comercial I | F94: 34672 | G94: F | H94: Casado(a) | I94: 43004 | K94: N/A - Empleado | L94: Activo | M94: Ventas | N94: Feria de empleo | O94: Dentro de lo Esperado | P94: 2 | Q94: 4 | R94: 0 | S94: 44166 | T94: =IF(L94="Activo",(DATE(2024,1,1)-I94)/365,(J94-I94)/365) -> 6.2684932
A95: Josefina Calderón | B95: 1312063714 | C95: 3 | D95: 7500 | E95: Analista Comercial II | F95: 35206 | G95: F | H95: Casado(a) | I95: 43226 | K95: N/A - Empleado | L95: Activo | M95: Ventas | N95: Feria de empleo | O95: Dentro de lo Esperado | P95: 2.81 | Q95: 3 | R95: 0 | S95: 44166 | T95: =IF(L95="Activo",(DATE(2024,1,1)-I95)/365,(J95-I95)/365) -> 5.660274
A96: Damián Córdoba | B96: 1111030503 | C96: 3 | D96: 7500 | E96: Analista Comercial II | F96: 34644 | G96: M | H96: Soltero | I96: 43588 | K96: N/A - Empleado | L96: Activo | M96: Ventas | N96: Web de empleo | O96: Dentro de lo Esperado | P96: 1.77 | Q96: 4 | R96: 0 | S96: 44166 | T96: =IF(L96="Activo",(DATE(2024,1,1)-I96)/365,(J96-I96)/365) -> 4.6684932
A97: Samuel Martínez | B97: 1504073313 | C97: 3 | D97: 7500 | E97: Analista Comercial II | F97: 29407 | G97: M | H97: Casado(a) | I97: 44467 | K97: N/A - Empleado | L97: Activo | M97: Ventas | N97: Indicación de empleados | O97: Dentro de lo Esperado | P97: 3.31 | Q97: 5 | R97: 0 | S97: 44166 | T97: =IF(L97="Activo",(DATE(2024,1,1)-I97)/365,(J97-I97)/365) -> 2.260274
A98: Erin Ávalos | B98: 1409070567 | C98: 4 | D98: 8600 | E98: Analista Comercial II | F98: 34191 | G98: F | H98: Soltero | I98: 43373 | K98: N/A - Empleado | L98: Activo | M98: Ventas | N98: Feria de empleo | O98: Por encima de lo Esperado | P98: 4.77 | Q98: 5 | R98: 0 | S98: 44166 | T98: =IF(L98="Activo",(DATE(2024,1,1)-I98)/365,(J98-I98)/365) -> 5.2575342
A99: Alejo Cuello | B99: 1411071302 | C99: 3 | D99: 8600 | E99: Analista Comercial II | F99: 25076 | G99: M | H99: Soltero | I99: 43259 | K99: N/A - Empleado | L99: Activo | M99: Ventas | N99: Web de empleo | O99: Dentro de lo Esperado | P99: 1.64 | Q99: 3 | R99: 0 | S99: 44166 | T99: =IF(L99="Activo",(DATE(2024,1,1)-I99)/365,(J99-I99)/365) -> 5.569863
A100: Alexia Farías | B100: 1203032099 | C100: 3 | D100: 8600 | E100: Analista Comercial II | F100: 34598 | G100: F | H100: Soltero | I100: 44607 | K100: N/A - Empleado | L100: Activo | M100: Ventas | N100: Web de empleo | O100: Dentro de lo Esperado | P100: 1.72 | Q100: 5 | R100: 0 | S100: 44166 | T100: =IF(L100="Activo",(DATE(2024,1,1)-I100)/365,(J100-I100)/365) -> 1.8767123
A101: Daniel Moyano | B101: 1203038888 | C101: 1 | D101: 8600 | E101: Analista Comercial II | F101: 29102 | G101: M | H101: Casado(a) | I101: 44534 | K101: N/A - Empleado | L101: Activo | M101: Ventas | N101: Web de la Empresa | O101: Por debajo de lo esperado | P101: 1.81 | Q101: 2 | R101: 0 | S101: 44166 | T101: =IF(L101="Activo",(DATE(2024,1,1)-I101)/365,(J101-I101)/365) -> 2.0767123
A102: Mateo Castaño | B102: 1104025008 | C102: 3 | D102: 8000 | E102: Analista Comercial II | F102: 31011 | G102: M | H102: Soltero | I102: 44061 | K102: N/A - Empleado | L102: Activo | M102: Ventas | N102: Web de empleo | O102: Dentro de lo Esperado | P102: 2.19 | Q102: 5 | R102: 0 | S102: 44166 | T102: =IF(L102="Activo",(DATE(2024,1,1)-I102)/365,(J102-I102)/365) -> 3.3726027
A103: Ignacio Patiño | B103: 1209048771 | C103: 3 | D103: 8600 | E103: Analista Comercial II | F103: 27703 | G103: M | H103: Soltero | I103: 43599 | K103: N/A - Empleado | L103: Activo | M103: Ventas | N103: Indicación de empleados | O103: Dentro de lo Esperado | P103: 2.94 | Q103: 5 | R103: 0 | S103: 44166 | T103: =IF(L103="Activo",(DATE(2024,1,1)-I103)/365,(J103-I103)/365) -> 4.6383562
A104: Antonio Greco | B104: 1209049326 | C104: 3 | D104: 8000 | E104: Analista Comercial II | F104: 32513 | G104: M | H104: Casado(a) | I104: 45084 | K104: N/A - Empleado | L104: Activo | M104: Ventas | N104: Web de empleo | O104: Dentro de lo Esperado | P104: 2.91 | Q104: 4 | R104: 0 | S104: 44166 | T104: =IF(L104="Activo",(DATE(2024,1,1)-I104)/365,(J104-I104)/365) -> 0.56986301
A105: Gabriela Maciel | B105: 1111030684 | C105: 3 | D105: 8000 | E105: Analista Comercial II | F105: 34423 | G105: F | H105: Soltero | I105: 44049 | K105: N/A - Empleado | L105: Activo | M105: Ventas | N105: Web de empleo | O105: Dentro de lo Esperado | P105: 5 | Q105: 5 | R105: 0 | S105: 44166 | T105: =IF(L105="Activo",(DATE(2024,1,1)-I105)/365,(J105-I105)/365) -> 3.4054795
... A141: Simón Verón | B141: 1011022818 | C141: 3 | D141: 4840 | E141: Técnico de Producción II | F141: 29860 | G141: M | H141: Soltero | I141: 44425 | K141: N/A - Empleado | L141: Activo | M141: Producción | N141: Indicación de empleados | O141: Dentro de lo Esperado | P141: 3.11 | Q141: 5 | R141: 0 | S141: 44166 | T141: =IF(L141="Activo",(DATE(2024,1,1)-I141)/365,(J141-I141)/365) -> 2.3753425
A142: Lucio Montenegro | B142: 1201431274 | C142: 3 | D142: 5500 | E142: Técnico de Producción II | F142: 30937 | G142: M | H142: Soltero | I142: 43291 | K142: N/A - Empleado | L142: Activo | M142: Producción | N142: Web de empleo | O142: Dentro de lo Esperado | P142: 3.96 | Q142: 4 | R142: 0 | S142: 44166 | T142: =IF(L142="Activo",(DATE(2024,1,1)-I142)/365,(J142-I142)/365) -> 5.4821918
A143: Victoria Mayorga | B143: 1108028351 | C143: 3 | D143: 5940 | E143: Técnico de Producción II | F143: 32365 | G143: F | H143: Soltero | I143: 44103 | K143: N/A - Empleado | L143: Activo | M143: Producción | N143: Indicación de empleados | O143: Dentro de lo Esperado | P143: 2.57 | Q143: 5 | R143: 0 | S143: 44166 | T143: =IF(L143="Activo",(DATE(2024,1,1)-I143)/365,(J143-I143)/365) -> 3.2575342
A144: Sabrina Gaitán | B144: 1001103149 | C144: 4 | D144: 5500 | E144: Técnico de Producción II | F144: 27507 | G144: F | H144: Soltero | I144: 43963 | K144: N/A - Empleado | L144: Activo | M144: Producción | N144: Web de la Empresa | O144: Por encima de lo Esperado | P144: 2.55 | Q144: 2.5 | R144: 0 | S144: 44166 | T144: =IF(L144="Activo",(DATE(2024,1,1)-I144)/365,(J144-I144)/365) -> 3.6410959
A145: Horacio Bianchi | B145: 1012023010 | C145: 3 | D145: 5335 | E145: Técnico de Producción II | F145: 33181 | G145: M | H145: Soltero | I145: 44383 | K145: N/A - Empleado | L145: Activo | M145: Producción | N145: Indicación de empleados | O145: Dentro de lo Esperado | P145: 4.07 | Q145: 4 | R145: 0 | S145: 44166 | T145: =IF(L145="Activo",(DATE(2024,1,1)-I145)/365,(J145-I145)/365) -> 2.490411
A146: María Paz Villafañe | B146: 1403066125 | C146: 2 | D146: 5940 | E146: Técnico de Producción II | F146: 34962 | G146: F | H146: Soltero | I146: 43193 | K146: N/A - Empleado | L146: Activo | M146: Producción | N146: Web de la Empresa | O146: Por debajo de lo esperado | P146: 1.16 | Q146: 3 | R146: 0 | S146: 44166 | T146: =IF(L146="Activo",(DATE(2024,1,1)-I146)/365,(J146-I146)/365) -> 5.7506849
A147: Tiana Kessler | B147: 1105025661 | C147: 1 | D147: 5280 | E147: Técnico de Producción II | F147: 34570 | G147: F | H147: Soltero | I147: 44383 | K147: N/A - Empleado | L147: Activo | M147: Producción | N147: Web de empleo | O147: Por debajo de lo esperado | P147: 4.59 | Q147: 1 | R147: 0 | S147: 44166 | T147: =IF(L147="Activo",(DATE(2024,1,1)-I147)/365,(J147-I147)/365) -> 2.490411
A148: Rommel Villarroel | B148: 1301052436 | C148: 3 | D148: 6380 | E148: Técnico de Producción II | F148: 28866 | G148: M | H148: Soltero | I148: 43963 | K148: N/A - Empleado | L148: Activo | M148: Producción | N148: Feria de empleo | O148: Dentro de lo Esperado | P148: 4.29 | Q148: 5 | R148: 0 | S148: 44166 | T148: =IF(L148="Activo",(DATE(2024,1,1)-I148)/365,(J148-I148)/365) -> 3.6410959
A149: Alan Bertolini | B149: 1101023457 | C149: 3 | D149: 4840 | E149: Técnico de Producción II | F149: 32350 | G149: M | H149: Soltero | I149: 44467 | K149: N/A - Empleado | L149: Activo | M149: Producción | N149: Indicación de empleados | O149: Dentro de lo Esperado | P149: 3.19 | Q149: 3 | R149: 0 | S149: 44166 | T149: =IF(L149="Activo",(DATE(2024,1,1)-I149)/365,(J149-I149)/365) -> 2.260274
A150: Débora Meza | B150: 1402065085 | C150: 3 | D150: 5280 | E150: Técnico de Producción II | F150: 33872 | G150: F | H150: Soltero | I150: 44243 | K150: N/A - Empleado | L150: Activo | M150: Producción | N150: Web de empleo | O150: Dentro de lo Esperado | P150: 4 | Q150: 4 | R150: 0 | S150: 44166 | T150: =IF(L150="Activo",(DATE(2024,1,1)-I150)/365,(J150-I150)/365) -> 2.8739726
A151: Reneh Scarpatti | B151: 1103024924 | C151: 3 | D151: 6160 | E151: Técnico de Producción II | F151: 35615 | G151: F | H151: Soltero | I151: 44686 | K151: N/A - Empleado | L151: Activo | M151: Producción | N151: Feria de empleo | O151: Dentro de lo Esperado | P151: 2.63 | Q151: 3 | R151: 0 | S151: 44166 | T151: =IF(L151="Activo",(DATE(2024,1,1)-I151)/365,(J151-I151)/365) -> 1.660274
A152: Jimena Lencina | B152: 1110029623 | C152: 3 | D152: 5060 | E152: Técnico de Producción II | F152: 29822 | G152: F | H152: Casado(a) | I152: 45143 | K152: N/A - Empleado | L152: Activo | M152: Producción | N152: Indicación de empleados | O152: Dentro de lo Esperado | P152: 5 | Q152: 3 | R152: 0 | S152: 44166 | T152: =IF(L152="Activo",(DATE(2024,1,1)-I152)/365,(J152-I152)/365) -> 0.40821918
A153: Osdina Brizuela | B153: 1402065303 | C153: 3 | D153: 11880 | E153: Gerente Comercial | F153: 34807 | G153: F | H153: Soltero | I153: 44320 | K153: N/A - Empleado | L153: Activo | M153: Ventas | N153: Web de empleo | O153: Dentro de lo Esperado | P153: 4.62 | Q153: 4 | R153: 0 | S153: 44166 | T153: =IF(L153="Activo",(DATE(2024,1,1)-I153)/365,(J153-I153)/365) -> 2.6630137
A154: Morhell Santoro | B154: 1499902910 | C154: 2 | D154: 12320 | E154: Gerente Comercial | F154: 32735 | G154: M | H154: Soltero | I154: 44333 | K154: N/A - Empleado | L154: Activo | M154: Ventas | N154: Web de empleo | O154: Por debajo de lo esperado | P154: 1.62 | Q154: 3 | R154: 0 | S154: 44166 | T154: =IF(L154="Activo",(DATE(2024,1,1)-I154)/365,(J154-I154)/365) -> 2.6273973
... A198: Romina Falcón | B198: 1012023185 | C198: 3 | D198: 10835 | E198: Ingeniero de Software | F198: 33442 | G198: F | H198: Casado(a) | I198: 43596 | K198: N/A - Empleado | L198: Activo | M198: TI | N198: Web de empleo | O198: Dentro de lo Esperado | P198: 1.74 | Q198: 3 | R198: 6 | S198: 44166 | T198: =IF(L198="Activo",(DATE(2024,1,1)-I198)/365,(J198-I198)/365) -> 4.6465753
A199: Germán Puglisi | B199: 1201431324 | C199: 4 | D199: 10560 | E199: Ingeniero de Software | F199: 32297 | G199: M | H199: Soltero | I199: 44383 | K199: N/A - Empleado | L199: Activo | M199: TI | N199: Web de la Empresa | O199: Por encima de lo Esperado | P199: 2.61 | Q199: 5 | R199: 5 | S199: 44166 | T199: =IF(L199="Activo",(DATE(2024,1,1)-I199)/365,(J199-I199)/365) -> 2.490411
A200: Daniel Morresi | B200: 1001644719 | C200: 3 | D200: 5940 | E200: Gerente de Ing. Software | F200: 26258 | G200: M | H200: Soltero | I200: 43326 | K200: N/A - Empleado | L200: Activo | M200: TI | N200: Web de empleo | O200: Dentro de lo Esperado | P200: 3.84 | Q200: 3 | R200: 5 | S200: 44166 | T200: =IF(L200="Activo",(DATE(2024,1,1)-I200)/365,(J200-I200)/365) -> 5.3863014
A201: Joana Spinelli | B201: 1201431308 | C201: 3 | D201: 7689 | E201: Contador II | F201: 30786 | G201: F | H201: Casado(a) | I201: 42490 | K201: N/A - Empleado | L201: Activo | M201: Administrativo | N201: Feria de empleo | O201: Dentro de lo Esperado | P201: 5 | Q201: 3 | R201: 2 | S201: 44166 | T201: =IF(L201="Activo",(DATE(2024,1,1)-I201)/365,(J201-I201)/365) -> 7.6767123
A202: Laura Massaro | B202: 1307060188 | C202: 3 | D202: 7689 | E202: Contador II | F202: 33696 | G202: F | H202: Casado(a) | I202: 44607 | K202: N/A - Empleado | L202: Activo | M202: Administrativo | N202: Feria de empleo | O202: Dentro de lo Esperado | P202: 5 | Q202: 4 | R202: 3 | S202: 44166 | T202: =IF(L202="Activo",(DATE(2024,1,1)-I202)/365,(J202-I202)/365) -> 1.8767123
A203: Ishal Toscano | B203: 1010022337 | C203: 3 | D203: 13486 | E203: Gerente de TI | F203: 33394 | G203: F | H203: Soltero | I203: 45107 | K203: N/A - Empleado | L203: Activo | M203: TI | N203: Indicación de empleados | O203: Dentro de lo Esperado | P203: 5 | Q203: 5 | R203: 6 | S203: 44166 | T203: =IF(L203="Activo",(DATE(2024,1,1)-I203)/365,(J203-I203)/365) -> 0.50684932
A204: Verónica Di Santo | B204: 1411071312 | C204: 3 | D204: 11902 | E204: Ingeniero de Software II | F204: 20836 | G204: F | H204: Casado(a) | I204: 44479 | K204: N/A - Empleado | L204: Activo | M204: TI | N204: Indicación de empleados | O204: Dentro de lo Esperado | P204: 1.55 | Q204: 5 | R204: 8 | S204: 44166 | T204: =IF(L204="Activo",(DATE(2024,1,1)-I204)/365,(J204-I204)/365) -> 2.2273973
A205: Sebastián Lombardo | B205: 1108028108 | C205: 3 | D205: 12364 | E205: Ingeniero de Software II | F205: 33350 | G205: M | H205: Casado(a) | I205: 44479 | K205: N/A - Empleado | L205: Activo | M205: TI | N205: Indicación de empleados | O205: Dentro de lo Esperado | P205: 4.46 | Q205: 5 | R205: 6 | S205: 44166 | T205: =IF(L205="Activo",(DATE(2024,1,1)-I205)/365,(J205-I205)/365) -> 2.2273973
A206: María Sol Roca | B206: 904013591 | C206: 3 | D206: 11836 | E206: Ingeniero de Software II | F206: 32386 | G206: NB | H206: Casado(a) | I206: 45107 | K206: N/A - Empleado | L206: Activo | M206: TI | N206: Feria de empleo | O206: Dentro de lo Esperado | P206: 3.27 | Q206: 4 | R206: 5 | S206: 44166 | T206: =IF(L206="Activo",(DATE(2024,1,1)-I206)/365,(J206-I206)/365) -> 0.50684932
A207: Facundo Bellini | B207: 1308060959 | C207: 3 | D207: 11660 | E207: Ingeniero de Software II | F207: 25819 | G207: M | H207: Soltero | I207: 44479 | K207: N/A - Empleado | L207: Activo | M207: TI | N207: Indicación de empleados | O207: Dentro de lo Esperado | P207: 5 | Q207: 3 | R207: 4 | S207: 44166 | T207: =IF(L207="Activo",(DATE(2024,1,1)-I207)/365,(J207-I207)/365) -> 2.2273973
A208: Agostina Pellegrini | B208: 1301052347 | C208: 3 | D208: 12144 | E208: Ingeniero de Software II | F208: 30351 | G208: F | H208: Soltero | I208: 44649 | K208: N/A - Empleado | L208: Activo | M208: TI | N208: Indicación de empleados | O208: Dentro de lo Esperado | P208: 1.06 | Q208: 4 | R208: 8 | S208: 44166 | T208: =IF(L208="Activo",(DATE(2024,1,1)-I208)/365,(J208-I208)/365) -> 1.7616438
A209: Leana Vitale | B209: 1211050782 | C209: 3 | D209: 4730 | E209: Asistente Administrativo | F209: 33131 | G209: F | H209: Casado(a) | I209: 44423 | J209: 44665 | K209: Rendimiento | L209: Despedido | M209: Administrativo | N209: Web de empleo | O209: Por debajo de lo esperado | P209: 3.24 | Q209: 3 | R209: 4 | T209: =IF(L209="Activo",(DATE(2024,1,1)-I209)/365,(J209-I209)/365) -> 0.6630137
A210: Mónica Farinelli | B210: 711007713 | C210: 3 | D210: 4510 | E210: Asistente Administrativo | F210: 33767 | G210: F | H210: Casado(a) | I210: 43368 | J210: 44098 | K210: Cambio de Carrera | L210: Solicito despido | M210: Administrativo | N210: Feria de empleo | O210: Dentro de lo Esperado | P210: 3.8 | Q210: 4 | R210: 4 | T210: =IF(L210="Activo",(DATE(2024,1,1)-I210)/365,(J210-I210)/365) -> 2
A211: Francis Giordano | B211: 1102024056 | C211: 3 | D211: 9460 | E211: Analista de Suporte de TI | F211: 33331 | G211: F | H211: Soltero | I211: 44383 | J211: 44903 | K211: Rendimiento | L211: Despedido | M211: TI | N211: Web de empleo | O211: Por debajo de lo esperado | P211: 1.87 | Q211: 4 | R211: 5 | T211: =IF(L211="Activo",(DATE(2024,1,1)-I211)/365,(J211-I211)/365) -> 1.4246575
A212: Silvia Caputo | B212: 905013738 | C212: 3 | D212: 10670 | E212: Analista de Suporte de TI | F212: 28054 | G212: F | H212: Soltero | I212: 44607 | J212: 44634 | K212: Abandono | L212: Despedido | M212: TI | N212: Web de empleo | O212: Dentro de lo Esperado | P212: 1.87 | Q212: 4 | R212: 4 | T212: =IF(L212="Activo",(DATE(2024,1,1)-I212)/365,(J212-I212)/365) -> 0.073972603
A213: Nicolás De Luca | B213: 1410071156 | C213: 3 | D213: 8822 | E213: Analista de Suporte de TI | F213: 33426 | G213: M | H213: Casado(a) | I213: 44242 | J213: 44613 | K213: Abandono | L213: Despedido | M213: TI | N213: Indicación de empleados | O213: Dentro de lo Esperado | P213: 4.33 | Q213: 3 | R213: 7 | T213: =IF(L213="Activo",(DATE(2024,1,1)-I213)/365,(J213-I213)/365) -> 1.0164384
A214: Patricio Orlandi | B214: 1102023965 | C214: 3 | D214: 9020 | E214: Analista de Datos III | F214: 32636 | G214: M | H214: Casado(a) | I214: 44207 | J214: 44930 | K214: Rendimiento | L214: Despedido | M214: TI | N214: Web de empleo | O214: Por debajo de lo esperado | P214: 1.62 | Q214: 4 | R214: 5 | T214: =IF(L214="Activo",(DATE(2024,1,1)-I214)/365,(J214-I214)/365) -> 1.9808219
...

Sheet Análisis - Respuestas
A1: PEOPLE ANALYTICS
A2: Evaluación de Empleados Activos
A4: 1 - ¿Cuántos empleados activos hay actualmente en la empresa?
B6: Deparmento | C6: Qtd | D6: % | F6: Status | G6: Qtd
B7: Producción | C7: =COUNTIFS(BD!$M:$M,'Análisis - Respuestas'!B7,BD!$L:$L,"Activo") -> 125 | D7: =C7/$C$11 -> 0.60386473 | F7: Activo | G7: =COUNTIFS(BD!$L:$L,F7) -> 207
B8: Ventas | C8: =COUNTIFS(BD!$M:$M,'Análisis - Respuestas'!B8,BD!$L:$L,"Activo") -> 27 | D8: =C8/$C$11 -> 0.13043478 | F8: Despedido | G8: =COUNTIFS(BD!$L:$L,F8) -> 24
B9: Administrativo | C9: =COUNTIFS(BD!$M:$M,'Análisis - Respuestas'!B9,BD!$L:$L,"Activo") -> 8 | D9: =C9/$C$11 -> 0.038647343 | F9: Solicito despido | G9: =COUNTIFS(BD!$L:$L,F9) -> 79
B10: TI | C10: =COUNTIFS(BD!$M:$M,'Análisis - Respuestas'!B10,BD!$L:$L,"Activo") -> 47 | D10: =C10/$C$11 -> 0.22705314 | F10: Total | G10: =SUM(G7:G9) -> 310
B11: Total | C11: =SUM(C7:C10) -> 207 | D11: =SUM(D7:D10) -> 1
A14: 2 - ¿Cuál es el costo de nómina mensual de esta empresa? / ¿Qué porcentaje de diversidad maneja la empresa?
B16: Empleados Activos | C16: Qtd | D16: % | E16: Costo mensual
B17: Femenino | C17: =COUNTIFS(BD!$G:$G,"F",BD!$L:$L,"Activo") -> 116 | D17: =C17/$C$20 -> 0.56038647 | E17: =SUMIFS(BD!$D:$D,BD!$L:$L,"Activo",BD!$G:$G,"F") -> 755850
B18: Masculino | C18: =COUNTIFS(BD!$G:$G,"M",BD!$L:$L,"Activo") -> 89 | D18: =C18/$C$20 -> 0.42995169 | E18: =SUMIFS(BD!$D:$D,BD!$L:$L,"Activo",BD!$G:$G,"M") -> 612864
B19: No Binario | C19: =COUNTIFS(BD!$G:$G,"NB",BD!$L:$L,"Activo") -> 2 | D19: =C19/$C$20 -> 0.0096618357 | E19: =SUMIFS(BD!$D:$D,BD!$L:$L,"Activo",BD!$G:$G,"NB") -> 24156
B20: Total | C20: =SUM(C17:C19) -> 207 | D20: =SUM(D17:D19) -> 1 | E20: =SUM(E17:E19) -> 1392870
A23: 3 - ¿Cuál es la principal fuente de contratación de la empresa? / 4 - De los miembros activos, ¿Qué porcentaje se basó en referencias de empleados?
B25: Fuente Reclutamiento | C25: Total BD | D25: Total Activos | E25: % Activos
B26: Web de la Empresa | C26: =COUNTIFS(BD!$N:$N,'Análisis - Respuestas'!B26) -> 61 | D26: =COUNTIFS(BD!$N:$N,'Análisis - Respuestas'!B26,BD!$L:$L,"Activo") -> 32 | E26: =D26/$D$30 -> 0.15458937
B27: Indicación de empleados | C27: =COUNTIFS(BD!$N:$N,'Análisis - Respuestas'!B27) -> 54 | D27: =COUNTIFS(BD!$N:$N,'Análisis - Respuestas'!B27,BD!$L:$L,"Activo") -> 43 | E27: =D27/$D$30 -> 0.20772947
B28: Web de empleo | C28: =COUNTIFS(BD!$N:$N,'Análisis - Respuestas'!B28) -> 129 | D28: =COUNTIFS(BD!$N:$N,'Análisis - Respuestas'!B28,BD!$L:$L,"Activo") -> 87 | E28: =D28/$D$30 -> 0.42028986
B29: Feria de empleo | C29: =COUNTIFS(BD!$N:$N,'Análisis - Respuestas'!B29) -> 66 | D29: =COUNTIFS(BD!$N:$N,'Análisis - Respuestas'!B29,BD!$L:$L,"Activo") -> 45 | E29: =D29/$D$30 -> 0.2173913
B30: Total | C30: =SUM(C26:C29) -> 310 | D30: =SUM(D26:D29) -> 207 | E30: =SUM(E26:E29) -> 1
A33: 5 - Según la última evaluación de desempeño, ¿Qué porcentaje de empleados activos se desempeñó por debajo de las expectativas? | L33: Siempre es bueno investigar o traer información adicional
B35: Registro de Rendimiento | C35: Activos | D35: % Activos
B36: Por encima de lo Esperado | C36: =COUNTIFS(BD!$O:$O, 'Análisis - Respuestas'!B36,BD!$L:$L,"Activo") -> 29 | D36: =C36/$C$39 -> 0.14009662
B37: Dentro de lo Esperado | C37: =COUNTIFS(BD!$O:$O, 'Análisis - Respuestas'!B37,BD!$L:$L,"Activo") -> 162 | D37: =C37/$C$39 -> 0.7826087
B38: Por debajo de lo esperado | C38: =COUNTIFS(BD!$O:$O, 'Análisis - Respuestas'!B38,BD!$L:$L,"Activo") -> 16 | D38: =C38/$C$39 -> 0.077294686
B39: Total | C39: =SUM(C36:C38) -> 207 | D39: =SUM(D36:D38) -> 1
A42: 6 - De los profesionales en activo, ¿Cuál es el promedio de años que llevan trabajando en esta empresa?
B44: Status | C44: Tiempo Medio Años 24
B45: Activo | C45: =AVERAGEIF(BD!$L:$L,'Análisis - Respuestas'!B45,BD!$T:$T) -> 3.3527099
B46: Despedido | C46: =AVERAGEIF(BD!$L:$L,'Análisis - Respuestas'!B46,BD!$T:$T) -> 1.7017123
B47: Solicito despido | C47: =AVERAGEIF(BD!$L:$L,'Análisis - Respuestas'!B47,BD!$T:$T) -> 2.4492804
B48: Total | C48: =AVERAGE(C45:C47) -> 2.5012342
A51: 7 - ¿Qué departamento representó el mayor nivel de satisfacción en la última encuesta realizada? (Considerando sólo los empleados activos).
B53: Deparmento | C53: Indice de Satisfacción*
B54: Producción | C54: =AVERAGEIFS(BD!$Q:$Q,BD!$L:$L,"Activo",BD!$M:$M,'Análisis - Respuestas'!B54) -> 3.8232
B55: Ventas | C55: =AVERAGEIFS(BD!$Q:$Q,BD!$L:$L,"Activo",BD!$M:$M,'Análisis - Respuestas'!B55) -> 3.8888889
B56: Administrativo | C56: =AVERAGEIFS(BD!$Q:$Q,BD!$L:$L,"Activo",BD!$M:$M,'Análisis - Respuestas'!B56) -> 3.5
B57: TI | C57: =AVERAGEIFS(BD!$Q:$Q,BD!$L:$L,"Activo",BD!$M:$M,'Análisis - Respuestas'!B57) -> 4.0425532
B58: Total | C58: =AVERAGEIFS(BD!$Q:$Q,BD!$L:$L,"Activo") -> 3.8690821 | D58: *El total del índice no se puede calcular con un promedio simple, debe ser solo de los activos ya que entoces se estaría considerando el mismo peso para todos los departamentos sin contar con la cantidad de empleados de cada uno.
A59: *Considerando únicamente a los empleados activos.
A62: 8 - ¿Existe una correlación entre la satisfacción de los empleados y el salario?
A82: Respuesta: En base al gráfico de dispersión, no se visualiza una correlación entre las variables.
A85: Evaluación de Empleados Inactivos
A87: 1 - ¿Cuántas personas fueron despedidas de la plantilla de la empresa entre 2020 y 2023? De estas personas, ¿Cuántas fueron despedidas y cuántas solicitaron el despido?
B89: Status | C89: Qtd
B90: Despedido | C90: =COUNTIFS(BD!$L:$L,'Análisis - Respuestas'!B90) -> 24
B91: Solicito despido | C91: =COUNTIFS(BD!$L:$L,'Análisis - Respuestas'!B91) -> 79
B92: Total | C92: =SUM(C90:C91) -> 103
A95: 2 - De los empleados que solicitaron el despido, ¿Cuáles fueron los motivos y sus respectivos porcentajes?
B97: Empleados que solicitaron el Despido | F97: Total de Empleados Inactivos
B98: Motivo Salida | C98: Qtd | D98: % | F98: Motivo Salida | G98: Qtd | H98: %
B99: Rendimiento | C99: =COUNTIFS(BD!$K:$K,'Análisis - Respuestas'!B99,BD!$L:$L,"Solicito despido") -> 0 | D99: =C99/$C$106 -> 0 | F99: Rendimiento | G99: =COUNTIFS(BD!$K:$K,'Análisis - Respuestas'!F99) -> 14 | H99: =G99/$G$106 -> 0.13592233
B100: Cambio de Carrera | C100: =COUNTIFS(BD!$K:$K,'Análisis - Respuestas'!B100,BD!$L:$L,"Solicito despido") -> 31 | D100: =C100/$C$106 -> 0.39240506 | F100: Cambio de Carrera | G100: =COUNTIFS(BD!$K:$K,'Análisis - Respuestas'!F100) -> 31 | H100: =G100/$G$106 -> 0.30097087
B101: Abandono | C101: =COUNTIFS(BD!$K:$K,'Análisis - Respuestas'!B101,BD!$L:$L,"Solicito despido") -> 0 | D101: =C101/$C$106 -> 0 | F101: Abandono | G101: =COUNTIFS(BD!$K:$K,'Análisis - Respuestas'!F101) -> 3 | H101: =G101/$G$106 -> 0.029126214
B102: Infeliz | C102: =COUNTIFS(BD!$K:$K,'Análisis - Respuestas'!B102,BD!$L:$L,"Solicito despido") -> 40 | D102: =C102/$C$106 -> 0.50632911 | F102: Infeliz | G102: =COUNTIFS(BD!$K:$K,'Análisis - Respuestas'!F102) -> 40 | H102: =G102/$G$106 -> 0.38834951
B103: Exceso de Faltas | C103: =COUNTIFS(BD!$K:$K,'Análisis - Respuestas'!B103,BD!$L:$L,"Solicito despido") -> 0 | D103: =C103/$C$106 -> 0 | F103: Exceso de Faltas | G103: =COUNTIFS(BD!$K:$K,'Análisis - Respuestas'!F103) -> 6 | H103: =G103/$G$106 -> 0.058252427
B104: Propuesta de la competencia | C104: =COUNTIFS(BD!$K:$K,'Análisis - Respuestas'!B104,BD!$L:$L,"Solicito despido") -> 8 | D104: =C104/$C$106 -> 0.10126582 | F104: Propuesta de la competencia | G104: =COUNTIFS(BD!$K:$K,'Análisis - Respuestas'!F104) -> 8 | H104: =G104/$G$106 -> 0.077669903
B105: Mal comportamiento | C105: =COUNTIFS(BD!$K:$K,'Análisis - Respuestas'!B105,BD!$L:$L,"Solicito despido") -> 0 | D105: =C105/$C$106 -> 0 | F105: Mal comportamiento | G105: =COUNTIFS(BD!$K:$K,'Análisis - Respuestas'!F105) -> 1 | H105: =G105/$G$106 -> 0.0097087379
B106: Total | C106: =SUM(C99:C105) -> 79 | D106: =SUM(D99:D105) -> 1 | F106: Total | G106: =SUM(G99:G105) -> 103 | H106: =SUM(H99:H105) -> 1
A109: 3 - Con base en las solicitudes de despido, ¿Cuáles pueden ser los posibles problemas en algún departamento?
F111: Seleccione el Departamento | G111: Producción
B112: Empleados que solicitaron el Despido | F112: Empleados que solicitaron el Despido
B113: Deparmento | C113: Qtd | D113: % | F113: Motivo Salida | G113: Qtd | H113: % | I113: % Total Inactivos
B114: Producción | C114: =COUNTIFS(BD!$M:$M,'Análisis - Respuestas'!B114,BD!$L:$L,"Solicito despido") -> 69 | D114: =C114/$C$118 -> 0.87341772 | F114: Rendimiento | G114: =COUNTIFS(BD!$K:$K,'Análisis - Respuestas'!F114,BD!$L:$L,"Solicito despido",BD!$M:$M,'Análisis - Respuestas'!$G$111) -> 0 | H114: =G114/$G$121 -> 0 | I114: =G114/$C$121 -> 0
B115: Ventas | C115: =COUNTIFS(BD!$M:$M,'Análisis - Respuestas'!B115,BD!$L:$L,"Solicito despido") -> 3 | D115: =C115/$C$118 -> 0.037974684 | F115: Cambio de Carrera | G115: =COUNTIFS(BD!$K:$K,'Análisis - Respuestas'!F115,BD!$L:$L,"Solicito despido",BD!$M:$M,'Análisis - Respuestas'!$G$111) -> 25 | H115: =G115/$G$121 -> 0.36231884 | I115: =G115/$C$121 -> 0.24271845
B116: Administrativo | C116: =COUNTIFS(BD!$M:$M,'Análisis - Respuestas'!B116,BD!$L:$L,"Solicito despido") -> 2 | D116: =C116/$C$118 -> 0.025316456 | F116: Abandono | G116: =COUNTIFS(BD!$K:$K,'Análisis - Respuestas'!F116,BD!$L:$L,"Solicito despido",BD!$M:$M,'Análisis - Respuestas'!$G$111) -> 0 | H116: =G116/$G$121 -> 0 | I116: =G116/$C$121 -> 0
B117: TI | C117: =COUNTIFS(BD!$M:$M,'Análisis - Respuestas'!B117,BD!$L:$L,"Solicito despido") -> 5 | D117: =C117/$C$118 -> 0.063291139 | F117: Infeliz | G117: =COUNTIFS(BD!$K:$K,'Análisis - Respuestas'!F117,BD!$L:$L,"Solicito despido",BD!$M:$M,'Análisis - Respuestas'!$G$111) -> 37 | H117: =G117/$G$121 -> 0.53623188 | I117: =G117/$C$121 -> 0.3592233
B118: Total | C118: =SUM(C114:C117) -> 79 | D118: =SUM(D114:D117) -> 1 | F118: Exceso de Faltas | G118: =COUNTIFS(BD!$K:$K,'Análisis - Respuestas'!F118,BD!$L:$L,"Solicito despido",BD!$M:$M,'Análisis - Respuestas'!$G$111) -> 0 | H118: =G118/$G$121 -> 0 | I118: =G118/$C$121 -> 0
F119: Propuesta de la competencia | G119: =COUNTIFS(BD!$K:$K,'Análisis - Respuestas'!F119,BD!$L:$L,"Solicito despido",BD!$M:$M,'Análisis - Respuestas'!$G$111) -> 7 | H119: =G119/$G$121 -> 0.10144928 | I119: =G119/$C$121 -> 0.067961165
F120: Mal comportamiento | G120: =COUNTIFS(BD!$K:$K,'Análisis - Respuestas'!F120,BD!$L:$L,"Solicito despido",BD!$M:$M,'Análisis - Respuestas'!$G$111) -> 0 | H120: =G120/$G$121 -> 0 | I120: =G120/$C$121 -> 0
B121: Total Inactivos | C121: 103 | F121: Total | G121: =SUM(G114:G120) -> 69 | H121: =SUM(H114:H120) -> 1 | I121: =SUM(I114:I120) -> 0.66990291
A123: Respuesta: En el Departamento de Producción hay mayor cantidad de solicitudes de despido por infelicidad, lo cual puede traducirce en los siguientes problemas:
A124: - Posibles problemas de liderazgo o estilo de supervisión.
A125: - Sobrecarga operativa tras el crecimiento acelerado.
A126: - Falta de planes de desarrollo o reconocimiento.
A127: - Desalineación entre expectativas del rol y la realidad operativa.
A130: 4 - ¿Existe algún registro de despido de personas que se desempeñan por encima de las expectativas? ¿Cuál es la justificación?
B132: Empleados despedidos
B133: Desempeño | C133: Total Despedidos | D133: % Despedidos
B134: Por encima de lo Esperado | C134: =COUNTIFS(BD!$O:$O,'Análisis - Respuestas'!B134,BD!$L:$L,"Despedido") -> 1 | D134: =C134/$C$137 -> 0.041666667 | E134: Justificación: Mal comportamiento
B135: Dentro de lo Esperado | C135: =COUNTIFS(BD!$O:$O,'Análisis - Respuestas'!B135,BD!$L:$L,"Despedido") -> 5 | D135: =C135/$C$137 -> 0.20833333
B136: Por debajo de lo esperado | C136: =COUNTIFS(BD!$O:$O,'Análisis - Respuestas'!B136,BD!$L:$L,"Despedido") -> 18 | D136: =C136/$C$137 -> 0.75
B137: Total | C137: =SUM(C134:C136) -> 24 | D137: =SUM(D134:D136) -> 1
A140: 5 - ¿La empresa ha estado perdiendo empleados que se desempeñan por encima de las expectativas?, ¿Cuáles serían las sugerencias para superar esta situación?
F142: Seleccione los Items | G142: Por encima de lo Esperado | H142: Producción
B143: Empleados que solicitaron el despido | F143: Empleados que solicitaron el Despido
B144: Desempeño | C144: Total Solicito Despido | D144: % Sol. Despido | F144: Motivo Salida | G144: Qtd | H144: % | I144: % Total Inactivos
B145: Por encima de lo Esperado | C145: =COUNTIFS(BD!$O:$O,'Análisis - Respuestas'!B145,BD!$L:$L,"Solicito despido") -> 7 | D145: =C145/$C$148 -> 0.088607595 | F145: Rendimiento | G145: =COUNTIFS(BD!$K:$K,'Análisis - Respuestas'!F145,BD!$L:$L,"Solicito despido",BD!$O:$O,'Análisis - Respuestas'!$G$142,BD!$M:$M,'Análisis - Respuestas'!$H$142) -> 0 | H145: =IFERROR(G145/$G$152,0) -> 0 | I145: =G145/$C$152 -> 0
B146: Dentro de lo Esperado | C146: =COUNTIFS(BD!$O:$O,'Análisis - Respuestas'!B146,BD!$L:$L,"Solicito despido") -> 64 | D146: =C146/$C$148 -> 0.81012658 | F146: Cambio de Carrera | G146: =COUNTIFS(BD!$K:$K,'Análisis - Respuestas'!F146,BD!$L:$L,"Solicito despido",BD!$O:$O,'Análisis - Respuestas'!$G$142,BD!$M:$M,'Análisis - Respuestas'!$H$142) -> 1 | H146: =IFERROR(G146/$G$152,0) -> 0.16666667 | I146: =G146/$C$152 -> 0.0097087379
B147: Por debajo de lo esperado | C147: =COUNTIFS(BD!$O:$O,'Análisis - Respuestas'!B147,BD!$L:$L,"Solicito despido") -> 8 | D147: =C147/$C$148 -> 0.10126582 | F147: Abandono | G147: =COUNTIFS(BD!$K:$K,'Análisis - Respuestas'!F147,BD!$L:$L,"Solicito despido",BD!$O:$O,'Análisis - Respuestas'!$G$142,BD!$M:$M,'Análisis - Respuestas'!$H$142) -> 0 | H147: =IFERROR(G147/$G$152,0) -> 0 | I147: =G147/$C$152 -> 0
B148: Total | C148: =SUM(C145:C147) -> 79 | D148: =SUM(D145:D147) -> 1 | F148: Infeliz | G148: =COUNTIFS(BD!$K:$K,'Análisis - Respuestas'!F148,BD!$L:$L,"Solicito despido",BD!$O:$O,'Análisis - Respuestas'!$G$142,BD!$M:$M,'Análisis - Respuestas'!$H$142) -> 5 | H148: =IFERROR(G148/$G$152,0) -> 0.83333333 | I148: =G148/$C$152 -> 0.048543689
F149: Exceso de Faltas | G149: =COUNTIFS(BD!$K:$K,'Análisis - Respuestas'!F149,BD!$L:$L,"Solicito despido",BD!$O:$O,'Análisis - Respuestas'!$G$142,BD!$M:$M,'Análisis - Respuestas'!$H$142) -> 0 | H149: =IFERROR(G149/$G$152,0) -> 0 | I149: =G149/$C$152 -> 0
F150: Propuesta de la competencia | G150: =COUNTIFS(BD!$K:$K,'Análisis - Respuestas'!F150,BD!$L:$L,"Solicito despido",BD!$O:$O,'Análisis - Respuestas'!$G$142,BD!$M:$M,'Análisis - Respuestas'!$H$142) -> 0 | H150: =IFERROR(G150/$G$152,0) -> 0 | I150: =G150/$C$152 -> 0
F151: Mal comportamiento | G151: =COUNTIFS(BD!$K:$K,'Análisis - Respuestas'!F151,BD!$L:$L,"Solicito despido",BD!$O:$O,'Análisis - Respuestas'!$G$142,BD!$M:$M,'Análisis - Respuestas'!$H$142) -> 0 | H151: =IFERROR(G151/$G$152,0) -> 0 | I151: =G151/$C$152 -> 0
B152: Total Inactivos | C152: 103 | F152: Total | G152: =SUM(G145:G151) -> 6 | H152: =SUM(H145:H151) -> 1 | I152: =SUM(I145:I151) -> 0.058252427
A154: Respuesta: El departamento de Producción es el que pierde mayor cantidad de talentos con excelente desempeño y la razón es por insatisfacción, por lo tanto, se recomienda:
A155: - Implementar programas de liderazgo y gestión de personas en Producción.
A156: - Crear planes de carrera y crecimiento interno.
...
